bing_image_creator_api/__init__.py
bing_image_creator_api/__main__.py
bing_image_creator_api/api.py
bing_image_creator_api-0.6.0.dist-info/METADATA
bing_image_creator_api-0.6.0.dist-info/WHEEL
bing_image_creator_api-0.6.0.dist-info/RECORD
