Metadata-Version: 2.1
Name: bing-image-creator-api
Version: 0.6.0
Summary: 
Author: megahomyak
Author-email: g.megahomyak@gmail.com
Requires-Python: >=3.10,<4.0
Classifier: Programming Language :: Python :: 3
Classifier: Programming Language :: Python :: 3.10
Classifier: Programming Language :: Python :: 3.11
Classifier: Programming Language :: Python :: 3.12
Requires-Dist: aiohttp (>=3.9.1,<4.0.0)
Requires-Dist: beautifulsoup4 (>=4.12.2,<5.0.0)
